glycosphingotool/__init__.py
glycosphingotool/cli.py
glycosphingotool/dataio.py
glycosphingotool/nomenclature.py
glycosphingotool/reactions.py
glycosphingotool/utils.py
glycosphingotool-0.1.0.dist-info/METADATA
glycosphingotool-0.1.0.dist-info/WHEEL
glycosphingotool-0.1.0.dist-info/entry_points.txt
glycosphingotool-0.1.0.dist-info/top_level.txt
glycosphingotool-0.1.0.dist-info/RECORD
