Metadata-Version: 2.4
Name: glycosphingotool
Version: 0.1.0
Summary: A CLI to transform glycan nomenclature into SMILES and reactions
Author-email: Anastasia Sveshnikova <sveshnikova.ana@gmail.com>
Project-URL: Homepage, https://github.com/anasves/glycosphingotool
Project-URL: Issues, https://github.com/anasves/glycosphingotool/issues
Requires-Python: >=3.9
Requires-Dist: click>=8.1
Requires-Dist: rdkit>=2023.03.1
Requires-Dist: pandas>=1.4
Requires-Dist: networkx>=3.0
Requires-Dist: openpyxl>=3.1
Requires-Dist: rxnsmiles2rinchi
Requires-Dist: xlrd
